mendidenborak/__init__.py
mendidenborak/mendidenborak.py
mendidenborak-2.0.0.dist-info/AUTHORS.rst
mendidenborak-2.0.0.dist-info/LICENSE
mendidenborak-2.0.0.dist-info/METADATA
mendidenborak-2.0.0.dist-info/WHEEL
mendidenborak-2.0.0.dist-info/top_level.txt
mendidenborak-2.0.0.dist-info/RECORD
