Metadata-Version: 2.1
Name: mendidenborak
Version: 2.0.0
Summary: Mendiko ibilbide desberdinak oinez egiteko zenbat denbora beharko den kalkulatzeko paketea.
Home-page: https://github.com/ionlizarazu/mendidenborak
Author: Ion Lizarazu
Author-email: ilizarazu@codesyntax.com
License: GNU General Public License v3
Keywords: mendidenborak
Platform: UNKNOWN
Classifier: Development Status :: 2 - Pre-Alpha
Classifier: Intended Audience :: Developers
Classifier: License :: OSI Approved :: GNU General Public License v3 (GPLv3)
Classifier: Natural Language :: English
Classifier: Programming Language :: Python :: 3
Classifier: Programming Language :: Python :: 3.5
Classifier: Programming Language :: Python :: 3.6
Classifier: Programming Language :: Python :: 3.7
Classifier: Programming Language :: Python :: 3.8
Requires-Python: >=3.5
